[{"name": "pid", "value": "3226945698992467136", "domain": ".smartadserver.com", "path": "/", "expires": 1745259628, "httpOnly": false, "secure": false, "sameSite": "None"}, {"name": "TestIfCookieP", "value": "ok", "domain": ".smartadserver.com", "path": "/", "expires": 1745259628, "httpOnly": false, "secure": false, "sameSite": "None"}, {"name": "csync", "value": "106:vec:82515802717", "domain": ".smartadserver.com", "path": "/", "expires": 1742840428, "httpOnly": false, "secure": false, "sameSite": "None"}, {"name": "X-AB", "value": "b9bd00ec73544025b937f4253ff9de4c", "domain": "sc-static.net", "path": "/scevent.min.js", "expires": 1711298750, "httpOnly": false, "secure": true, "sameSite": "None"}, {"name": "ar_debug", "value": "1", "domain": ".pinterest.com", "path": "/", "expires": 1742757387, "httpOnly": true, "secure": true, "sameSite": "None"}, {"name": "_pinterest_ct_ua", "value": "\"TWc9PSZaWUgyZGRmejNQZmdtMVVGYTBCeW02MmtXcjl5R3JOTWpQdzdDV2JweWVLaHBSSkFiMkI2RzIwWWtIOVBUNE4xN05IR2tIZ2Q5MnJrQkljWVhJOFgvaS9IamhuYVpMRDJkeUx2Zm1YL05LST0ma0N5SC9neXJuNk9VMkJ4RnEyOEtxMlBrcVM0PQ==\"", "domain": ".ct.pinterest.com", "path": "/", "expires": 1742757387, "httpOnly": false, "secure": true, "sameSite": "None"}, {"name": "OptanonAlertBoxClosed", "value": "2024-03-22T19:27:28.126Z", "domain": ".leroymerlin.fr", "path": "/", "expires": 1726687648, "httpOnly": false, "secure": false, "sameSite": "Lax"}, {"name": "OptanonConsent", "value": "isGpcEnabled=0&datestamp=Fri+Mar+22+2024+20%3A27%3A28+GMT%2B0100+(West+Africa+Standard+Time)&version=202403.1.0&browserGpcFlag=0&isIABGlobal=false&hosts=&genVendors=&consentId=a213a737-d3d8-4c77-850c-4ce50be74d37&interactionCount=1&isAnonUser=1&landingPath=NotLandingPage&groups=C0001%3A1%2CC0002%3A1%2CC0003%3A1%2CC0004%3A1&AwaitingReconsent=false", "domain": ".leroymerlin.fr", "path": "/", "expires": 1726687648, "httpOnly": false, "secure": false, "sameSite": "Lax"}, {"name": "pa_privacy", "value": "%22optin%22", "domain": ".leroymerlin.fr", "path": "/", "expires": 1745263648, "httpOnly": false, "secure": true, "sameSite": "Lax"}, {"name": "iadvize-5601-consent", "value": "true", "domain": ".leroymerlin.fr", "path": "/", "expires": 1742671648, "httpOnly": false, "secure": true, "sameSite": "None"}, {"name": "iadvize-5601-vuid", "value": "1295bc9fb5424ef999704b44995b797e646c8234bc2b4", "domain": ".leroymerlin.fr", "path": "/", "expires": 1742671648, "httpOnly": false, "secure": true, "sameSite": "None"}, {"name": "_scid", "value": "e944f282-0733-4aa0-a382-8d9e6a95cca4", "domain": ".leroymerlin.fr", "path": "/", "expires": 1745322349, "httpOnly": false, "secure": false, "sameSite": "Lax"}, {"name": "_cs_c", "value": "1", "domain": ".leroymerlin.fr", "path": "/", "expires": 1745299651, "httpOnly": false, "secure": false, "sameSite": "Lax"}, {"name": "store", "value": "store=84|dateContext=20240322", "domain": ".leroymerlin.fr", "path": "/", "expires": 1745263653, "httpOnly": false, "secure": false, "sameSite": "Lax"}, {"name": "lmfr_store_id", "value": "84", "domain": ".leroymerlin.fr", "path": "/", "expires": 1745263653, "httpOnly": false, "secure": false, "sameSite": "Lax"}, {"name": "store_id", "value": "84", "domain": ".leroymerlin.fr", "path": "/", "expires": 1745263653, "httpOnly": false, "secure": false, "sameSite": "Lax"}, {"name": "customer_context", "value": "%7B%22auto_context%22%3A%22true%22%2C%22nearby_stores%22%3A%2211%2C30%2C32%22%2C%22city%22%3A%22Naaldwijk%22%2C%22latitude%22%3A%2251.9981%22%2C%22main_store%22%3A%2284%22%2C%22postcode%22%3A%222671%22%2C%22stores_name%22%3A%5B%7B%22name%22%3A%22Neuville-en-Ferrain+-+Lille+%22%2C%22id%22%3A%2284%22%7D%2C%7B%22name%22%3A%22Villeneuve-d%27Ascq+-+Lille%22%2C%22id%22%3A%2211%22%7D%2C%7B%22name%22%3A%22Grande-Synthe+-+Dunkerque%22%2C%22id%22%3A%2230%22%7D%2C%7B%22name%22%3A%22Lesquin+-+Lille%22%2C%22id%22%3A%2232%22%7D%5D%2C%22white_zone%22%3A%22false%22%2C%22longitude%22%3A%224.198%22%7D", "domain": ".leroymerlin.fr", "path": "/", "expires": 1745263653, "httpOnly": false, "secure": false, "sameSite": "Lax"}, {"name": "ab_cat", "value": "A-D", "domain": "www.leroymerlin.fr", "path": "/", "expires": 1716319653, "httpOnly": false, "secure": true, "sameSite": "None"}, {"name": "ab_lazy", "value": "on", "domain": "www.leroymerlin.fr", "path": "/", "expires": 1712950053, "httpOnly": false, "secure": true, "sameSite": "None"}, {"name": "search_ab_version", "value": "1", "domain": "www.leroymerlin.fr", "path": "/", "expires": 1742671653, "httpOnly": false, "secure": true, "sameSite": "None"}, {"name": "t2s-analytics", "value": "dcca71c9-515a-4a5a-8214-b78c7be045b2", "domain": "www.leroymerlin.fr", "path": "/", "expires": 1744831656, "httpOnly": false, "secure": true, "sameSite": "None"}, {"name": "_pcid", "value": "%7B%22browserId%22%3A%22lu31yaecfiwy95cw%22%2C%22_t%22%3A%22m9rgvrqk%7Clu31yaek%22%7D", "domain": ".leroymerlin.fr", "path": "/", "expires": 1745263594, "httpOnly": false, "secure": true, "sameSite": "Lax"}, {"name": "_pctx", "value": "%7Bu%7DN4IgrgzgpgThIC4B2YA2qA05owMoBcBDfSREQpAeyRCwgEt8oBJAE0RXSwH18yBbAJwwA5gDcYAR1QAfVGADMARgCehKKhABfIA", "domain": ".leroymerlin.fr", "path": "/", "expires": 1745263594, "httpOnly": false, "secure": true, "sameSite": "Lax"}, {"name": "_gcl_au", "value": "1.1.207290359.1711135649", "domain": ".leroymerlin.fr", "path": "/", "expires": 1718911649, "httpOnly": false, "secure": false, "sameSite": "None"}, {"name": "_vzbl_uid", "value": "IQzX0amVgbcHgT3W0Ukpp", "domain": "www.leroymerlin.fr", "path": "/", "expires": 1745385388, "httpOnly": false, "secure": false, "sameSite": "None"}, {"name": "_scid_r", "value": "e944f282-0733-4aa0-a382-8d9e6a95cca4", "domain": ".leroymerlin.fr", "path": "/", "expires": 1745408086, "httpOnly": false, "secure": false, "sameSite": "Lax"}, {"name": "_uetsid", "value": "3a1a18a0e88211eea32115d053219d7b", "domain": ".leroymerlin.fr", "path": "/", "expires": 1711307788, "httpOnly": false, "secure": false, "sameSite": "None"}, {"name": "_uetvid", "value": "3a1a20d0e88211eeb61865e156e01165", "domain": ".leroymerlin.fr", "path": "/", "expires": 1744917388, "httpOnly": false, "secure": false, "sameSite": "None"}, {"name": "vlz_uid", "value": "UuMoctj1qE6aY18xOwkZkjF4aKABIhIv", "domain": "www.leroymerlin.fr", "path": "/", "expires": 1742757388, "httpOnly": false, "secure": false, "sameSite": "None"}, {"name": "t2s-p", "value": "dcca71c9-515a-4a5a-8214-b78c7be045b2", "domain": "www.leroymerlin.fr", "path": "/", "expires": 1744917388, "httpOnly": false, "secure": true, "sameSite": "None"}, {"name": "_cs_id", "value": "23063cf1-546e-a5d5-d4ee-3490c6f021a3.1711135651.8.1711221388.1711216806.1618220803.1745299651692.1", "domain": ".leroymerlin.fr", "path": "/", "expires": 1745299651, "httpOnly": false, "secure": false, "sameSite": "Lax"}, {"name": "_cs_s", "value": "10.0.0.1711223188892", "domain": ".leroymerlin.fr", "path": "/", "expires": 1711223188, "httpOnly": false, "secure": false, "sameSite": "Lax"}, {"name": "_pin_unauth", "value": "dWlkPVpUQTBPV0UzTW1ZdE56UXdPQzAwWkRreExXSTNPR010TjJJeE56UmpPVFV3TURJeg", "domain": ".leroymerlin.fr", "path": "/", "expires": 1742757389, "httpOnly": false, "secure": false, "sameSite": "None"}, {"name": "_adv_id.lmf9ehdpz.dff7", "value": "2oo1zsa6pzeavptl.1711221386.0.1711221390..", "domain": ".leroymerlin.fr", "path": "/", "expires": 1745176589, "httpOnly": false, "secure": false, "sameSite": "None"}, {"name": "_adv_ses.lmf9ehdpz.dff7", "value": "5e6a79dcf19f8a90", "domain": "www.leroymerlin.fr", "path": "/", "expires": 1711223189, "httpOnly": false, "secure": false, "sameSite": "None"}, {"name": "_sc_cspv", "value": "https%3A%2F%2Ftr6.snapchat.com%2Fp", "domain": ".leroymerlin.fr", "path": "/", "expires": 1745408087, "httpOnly": false, "secure": false, "sameSite": "Lax"}, {"name": "mics_vid", "value": "82515802717", "domain": "www.leroymerlin.fr", "path": "/", "expires": 1726773390, "httpOnly": false, "secure": false, "sameSite": "None"}, {"name": "mics_lts", "value": "1711218027487", "domain": "www.leroymerlin.fr", "path": "/", "expires": 1726773390, "httpOnly": false, "secure": false, "sameSite": "None"}, {"name": "_dd_s", "value": "rum=0&expire=1711222816778", "domain": "www.leroymerlin.fr", "path": "/", "expires": 1711222816, "httpOnly": false, "secure": true, "sameSite": "None"}, {"name": "lm-csrf", "value": "k403HOh9Tu6SMV1cqw9AXDPwydpDL8FRbfh1UwF0aug=.1711223317476.DOIOdR9BB6c8cjv+M1VWGXjF1gknSTwtMa0gEu+uY34=", "domain": "www.leroymerlin.fr", "path": "/", "expires": -1, "httpOnly": false, "secure": true, "sameSite": "None"}, {"name": "datadome", "value": "ts4IYq8GpsfFQ7xTEtwOLJgloTm4Dvcg53YXhbGlkbfvH3FQbqMaXBlkNkkI3MPIS~z2PPzlldduzkHQc_4uw5sAHyMKjxGbl8XP4UeSIbepAkTgwWQ3l92w2Jawg~7Q", "domain": ".leroymerlin.fr", "path": "/", "expires": 1742759330, "httpOnly": false, "secure": true, "sameSite": "Lax"}, {"name": "CMPS", "value": "3393", "domain": ".casalemedia.com", "path": "/", "expires": 1718996064, "httpOnly": false, "secure": true, "sameSite": "None"}, {"name": "CMID", "value": "Zf8lXVVbLc8AAHfKAibFMgAA", "domain": ".casalemedia.com", "path": "/", "expires": 1742756065, "httpOnly": false, "secure": true, "sameSite": "None"}, {"name": "CMPRO", "value": "3393", "domain": ".casalemedia.com", "path": "/", "expires": 1718996065, "httpOnly": false, "secure": true, "sameSite": "None"}, {"name": "ApplicationGatewayAffinityV2CORS", "value": "1031c266a453736d8d6e7d661ca19285", "domain": "media.adeo.com", "path": "/", "expires": -1, "httpOnly": false, "secure": true, "sameSite": "None"}, {"name": "ApplicationGatewayAffinityV2", "value": "1031c266a453736d8d6e7d661ca19285", "domain": "media.adeo.com", "path": "/", "expires": -1, "httpOnly": false, "secure": false, "sameSite": "None"}, {"name": "JSESSIONID", "value": "08CA6CA325B4179BBB44F780CFBC6654", "domain": "media.adeo.com", "path": "/", "expires": -1, "httpOnly": true, "secure": true, "sameSite": "None"}, {"name": "g", "value": "eg0dP0gCrd3qKZeRdxxJ_1711212349472", "domain": ".creativecdn.com", "path": "/", "expires": 1742748352, "httpOnly": false, "secure": true, "sameSite": "None"}, {"name": "c", "value": "eg0dP0gCrd3qKZeRdxxJ_rQpvAj8RpVuyZpY4D5tO_1711212349472", "domain": ".creativecdn.com", "path": "/", "expires": 1742748352, "httpOnly": false, "secure": true, "sameSite": "None"}, {"name": "ts", "value": "1711212349", "domain": ".creativecdn.com", "path": "/", "expires": 1742748352, "httpOnly": false, "secure": true, "sameSite": "None"}, {"name": "ar_debug", "value": "1", "domain": ".creativecdn.com", "path": "/", "expires": 1742748349, "httpOnly": true, "secure": true, "sameSite": "None"}, {"name": "mics_vid", "value": "82515802717", "domain": ".mediarithmics.com", "path": "/", "expires": 1742754030, "httpOnly": true, "secure": true, "sameSite": "None"}, {"name": "mics_uaid", "value": "web:1:93126851-0430-45f7-b883-871d7f98a5d1", "domain": ".mediarithmics.com", "path": "/", "expires": 1742754030, "httpOnly": true, "secure": true, "sameSite": "None"}, {"name": "mics_lts", "value": "1711218027487", "domain": ".mediarithmics.com", "path": "/", "expires": 1742754030, "httpOnly": true, "secure": true, "sameSite": "None"}, {"name": "kamino_user", "value": "35179605-57c7-45cd-a9fd-fdb959497538", "domain": ".kaminoretail.io", "path": "/", "expires": 1742661956, "httpOnly": false, "secure": true, "sameSite": "None"}, {"name": "kamino_session", "value": "4fd0244c-1ffe-445d-ba69-d41ae591ebe8", "domain": ".kaminoretail.io", "path": "/", "expires": 1711226757, "httpOnly": true, "secure": true, "sameSite": "None"}, {"name": "kamino_optin", "value": "cmlkPWEyMTNhNzM3LWQzZDgtNGM3Ny04NTBjLTRjZTUwYmU3NGQzNyZjPTE3MTEzMDc3ODg3NDgmdnU9MTcyOTc5NzM4ODc0OA==", "domain": ".kaminoretail.io", "path": "/", "expires": 1742670990, "httpOnly": false, "secure": true, "sameSite": "None"}, {"name": "IDE", "value": "AHWqTUkcMc8SrQOHvta6n3iPpOsC3i5PT5n5hO_bsuoujLBUew9GjV7OC20N0SA6rLc", "domain": ".doubleclick.net", "path": "/", "expires": 1744908354, "httpOnly": true, "secure": true, "sameSite": "None"}, {"name": "mics_uaid", "value": "web:1053:45ee7666-4974-4b8e-bf7a-291b6d64f4af", "domain": ".valiuz.com", "path": "/", "expires": 1742754030, "httpOnly": true, "secure": true, "sameSite": "None"}, {"name": "uid", "value": "45ee7666-4974-4b8e-bf7a-291b6d64f4af", "domain": ".valiuz.com", "path": "/", "expires": 1742754030, "httpOnly": true, "secure": true, "sameSite": "None"}, {"name": "mics_vid", "value": "82515802717", "domain": ".valiuz.com", "path": "/", "expires": 1742754030, "httpOnly": true, "secure": true, "sameSite": "None"}, {"name": "mics_lts", "value": "1711218027487", "domain": ".valiuz.com", "path": "/", "expires": 1742754030, "httpOnly": true, "secure": true, "sameSite": "None"}, {"name": "vlzc", "value": "UuMoctj1qE6aY18xOwkZkjF4aKABIhIv", "domain": "web.valiuz.com", "path": "/", "expires": 1742757385, "httpOnly": true, "secure": true, "sameSite": "None"}, {"name": "MUID", "value": "385DE2B43F41674E0377F6FF3EC266E7", "domain": ".bing.com", "path": "/", "expires": 1744908348, "httpOnly": false, "secure": true, "sameSite": "None"}, {"name": "MSPTC", "value": "IENrwa6IPzdWWp0Znoihmm1MSOUxEq8GPZscci7mv3o", "domain": ".bing.com", "path": "/", "expires": 1744909809, "httpOnly": false, "secure": true, "sameSite": "None"}, {"name": "anj", "value": "dTM7k!M4/0CxrEQF']wIg2Il`hF'ng!fk#0b`'k[Fghe>_Ny_!/'atsH'z69qU+F4Sj'iZUGGzV+!+M)*:#B/q)cYOViJnoFvJ>Y[Y#$%DXvpE^if+ML<_*f!2>h9/+0J2!-4!a+$x]>", "domain": ".adnxs.com", "path": "/", "expires": 1718997389, "httpOnly": true, "secure": true, "sameSite": "None"}, {"name": "uuid2", "value": "8481672300343835486", "domain": ".adnxs.com", "path": "/", "expires": 1718997391, "httpOnly": true, "secure": true, "sameSite": "None"}]